audidata/__init__.py
audidata/utils.py
audidata/collate/__init__.py
audidata/collate/default.py
audidata/collate/update_collate.py
audidata/datasets/__init__.py
audidata/datasets/audiocaps.py
audidata/datasets/clotho.py
audidata/datasets/clotho_aqa.py
audidata/datasets/free_spoken_digit.py
audidata/datasets/gtzan.py
audidata/datasets/librispeech.py
audidata/datasets/ljspeech.py
audidata/datasets/maestro.py
audidata/datasets/musdb18hq.py
audidata/datasets/shutterstock.py
audidata/datasets/todo_esc50.py
audidata/datasets/todo_gmd.py
audidata/datasets/todo_isophonics.py
audidata/datasets/todo_magnatagatune.py
audidata/datasets/todo_slakh2100.py
audidata/datasets/todo_urmp.py
audidata/datasets/voicebank_demand.py
audidata/datasets/wavcaps.py
audidata/io/__init__.py
audidata/io/_midi.py
audidata/io/audio.py
audidata/io/crops.py
audidata/io/midi.py
audidata/samplers/__init__.py
audidata/samplers/_base.py
audidata/samplers/infinite_sampler.py
audidata/samplers/multi_datasets_batch_sampler.py
audidata/samplers/pseudo_random_sampler.py
audidata/samplers/random_song_sampler.py
audidata/tokenizers/__init__.py
audidata/tokenizers/_base.py
audidata/tokenizers/base.py
audidata/transforms/__init__.py
audidata/transforms/_audio.py
audidata/transforms/audio.py
audidata/transforms/midi.py
audidata/transforms/onehot.py
audidata/transforms/text.py
audidata-0.0.5.dist-info/licenses/LICENSE
audidata-0.0.5.dist-info/METADATA
audidata-0.0.5.dist-info/WHEEL
audidata-0.0.5.dist-info/top_level.txt
audidata-0.0.5.dist-info/RECORD
