Metadata-Version: 2.4
Name: audidata
Version: 0.0.5
Summary: Audio dataloaders
Home-page: https://github.com/AudioFans/audidata
Author: Qiuqiang Kong
Author-email: qiuqiangkong@gmail.com
Classifier: Programming Language :: Python :: 3
Classifier: License :: OSI Approved :: MIT License
Classifier: Operating System :: OS Independent
Requires-Python: >=3.5
License-File: LICENSE
Requires-Dist: numpy
Requires-Dist: torch
Requires-Dist: torchaudio
Requires-Dist: pretty_midi
Requires-Dist: pandas
Requires-Dist: pyyaml
Dynamic: author
Dynamic: author-email
Dynamic: classifier
Dynamic: description
Dynamic: description-content-type
Dynamic: home-page
Dynamic: license-file
Dynamic: requires-dist
Dynamic: requires-python
Dynamic: summary
